{
  "project_info": {
    "project_number": "175826842825",
    "firebase_url": "https://ritmacounterapp.firebaseio.com",
    "project_id": "ritmacounterapp",
    "storage_bucket": "ritmacounterapp.appspot.com"
  },
  "client": [
    {
      "client_info": {
        "mobilesdk_app_id": "1:175826842825:android:e8eb77321a3772b6698918",
        "android_client_info": {
          "package_name": "com.ritma.counterapp"
        }
      },
      "oauth_client": [
        {
          "client_id": "175826842825-92hht5g53m7lkj7kr46nu3ss9oubr92t.apps.googleusercontent.com",
          "client_type": 3
        }
      ],
      "api_key": [
        {
          "current_key": "AIzaSyAdu10-gSZd80Q13L3AAap7AyQitiBhdOY"
        }
      ],
      "services": {
        "appinvite_service": {
          "other_platform_oauth_client": [
            {
              "client_id": "175826842825-92hht5g53m7lkj7kr46nu3ss9oubr92t.apps.googleusercontent.com",
              "client_type": 3
            }
          ]
        }
      }
    }
  ],
  "configuration_version": "1"
}